gptransits/__init__.py
gptransits/component.py
gptransits/config_template.py
gptransits/convergence.py
gptransits/gp.py
gptransits/helper.py
gptransits/model.py
gptransits/plot.py
gptransits/settings.py
gptransits/stats.py
gptransits/transit.py
gptransits/version.py
gptransits-1.0.dist-info/LICENSE
gptransits-1.0.dist-info/METADATA
gptransits-1.0.dist-info/WHEEL
gptransits-1.0.dist-info/top_level.txt
gptransits-1.0.dist-info/zip-safe
gptransits-1.0.dist-info/RECORD
