Metadata-Version: 2.1
Name: gptransits
Version: 1.0
Summary: Fit planetary transits and stellar signals at the same time with the help of gaussian processes
Home-page: https://github.com/Fill4/gptransits
Author: Filipe Pereira
Author-email: filipe.pereira@astro.up.pt
License: MIT
Platform: UNKNOWN
Classifier: Programming Language :: Python :: 3.6
Classifier: Programming Language :: Python :: 3.7
Classifier: License :: OSI Approved :: MIT License
Classifier: Operating System :: OS Independent
Requires-Python: >=3.6
Requires-Dist: numpy
Requires-Dist: batman-package
Requires-Dist: pybind11
Requires-Dist: scipy
Requires-Dist: matplotlib
Requires-Dist: tqdm
Requires-Dist: corner
Requires-Dist: astropy (>=3.0.0)
Requires-Dist: emcee (==3.0rc2)
Requires-Dist: celerite (==0.3.0)
